ossa_scanner/__init__.py
ossa_scanner/cli.py
ossa_scanner/scanner.py
ossa_scanner/uploader.py
ossa_scanner/utils/__init__.py
ossa_scanner/utils/downloader.py
ossa_scanner/utils/hash_calculator.py
ossa_scanner/utils/os_detection.py
ossa_scanner/utils/package_manager.py
ossa_scanner/utils/swhid_calculator.py
ossa_scanner-0.1.11.dist-info/LICENSE
ossa_scanner-0.1.11.dist-info/METADATA
ossa_scanner-0.1.11.dist-info/WHEEL
ossa_scanner-0.1.11.dist-info/entry_points.txt
ossa_scanner-0.1.11.dist-info/top_level.txt
ossa_scanner-0.1.11.dist-info/RECORD
