Metadata-Version: 2.1
Name: ossa_scanner
Version: 0.1.11
Summary: Open Source Software Advisory generator for Core and Base Linux Packages.
Home-page: https://github.com/oscarvalenzuelab/ossa_scanner
Author: Oscar Valenzuela
Author-email: oscar.valenzuela.b@gmail.com
License: MIT
Keywords: linux packages SWHID open-source compliance ossa advisory
Classifier: Development Status :: 3 - Alpha
Classifier: Intended Audience :: Developers
Classifier: License :: OSI Approved :: MIT License
Classifier: Programming Language :: Python :: 3
Classifier: Programming Language :: Python :: 3.6
Classifier: Programming Language :: Python :: 3.7
Classifier: Programming Language :: Python :: 3.8
Classifier: Programming Language :: Python :: 3.9
Classifier: Programming Language :: Python :: 3.10
Classifier: Operating System :: POSIX :: Linux
Requires-Python: >=3.6
License-File: LICENSE
Requires-Dist: click
Requires-Dist: swh.model
Requires-Dist: distro
Requires-Dist: ssdeep
